gaspar/__init__.py
gaspar/__main__.py
gaspar/_version.py
gaspar/cli/__init__.py
gaspar/cli/main.py
gaspar/cli/progress.py
gaspar/cli/utils.py
gaspar/config/__init__.py
gaspar/config/base.py
gaspar/config/loader.py
gaspar/core/types.py
gaspar/core/analyzers/__init__.py
gaspar/core/analyzers/anomaly_detector.py
gaspar/core/analyzers/base.py
gaspar/core/analyzers/filter_generator.py
gaspar/core/models/__init__.py
gaspar/core/models/base.py
gaspar/core/models/factory.py
gaspar/core/models/ipa_rules.py
gaspar/core/models/openai_model.py
gaspar/core/processors/__init__.py
gaspar/core/processors/base.py
gaspar/core/processors/data_modeler.py
gaspar/core/processors/data_monitor.py
gaspar/core/processors/feature_processor.py
gaspar/core/processors/ipa_processor.py
gaspar/gaspar/config/loader.py
gaspar/pipeline/base.py
gaspar/pipeline/executor.py
gaspar/pipeline/steps/__init__.py
gaspar/pipeline/steps/analysis.py
gaspar/pipeline/steps/deployment.py
gaspar/pipeline/steps/detection.py
gaspar/pipeline/steps/modeling.py
gaspar/storage/__init__.py
gaspar/storage/azure.py
gaspar/storage/base.py
gaspar/storage/local.py
amadeus_os_gaspar-0.0.1.dist-info/METADATA
amadeus_os_gaspar-0.0.1.dist-info/WHEEL
amadeus_os_gaspar-0.0.1.dist-info/entry_points.txt
amadeus_os_gaspar-0.0.1.dist-info/licenses/LICENSE
amadeus_os_gaspar-0.0.1.dist-info/RECORD
