Metadata-Version: 2.4
Name: amadeus-os-gaspar
Version: 0.0.1
Summary: GenAI-powered System for Privacy incident Analysis and Recovery
License: MIT
License-File: LICENSE
Classifier: Development Status :: 4 - Beta
Classifier: Intended Audience :: Developers
Classifier: License :: OSI Approved :: MIT License
Classifier: Programming Language :: Python :: 3
Classifier: Programming Language :: Python :: 3.8
Classifier: Programming Language :: Python :: 3.9
Classifier: Programming Language :: Python :: 3.10
Requires-Python: >=3.8
Requires-Dist: aiofiles>=23.2.1
Requires-Dist: aiohttp>=3.8.1
Requires-Dist: anthropic>=0.3.0
Requires-Dist: azure-identity>=1.15.0
Requires-Dist: azure-storage-blob>=12.19.0
Requires-Dist: numpy>=1.24.0
Requires-Dist: openai>=1.0.0
Requires-Dist: pandas>=2.0.0
Requires-Dist: pydantic>=2.0
Requires-Dist: pyyaml>=6.0
Requires-Dist: scikit-learn>=1.2.0
Requires-Dist: tenacity>=8.2.0
